jerarquia/design.sv
/*
Name   : Nazim
Date   : 29th April, 2018
Design : 4_input Multiplexar
*/


module MUX (
    A,
    B,
    C,
    D,
    out,
    sel,
    en
);


//    Input    //
input logic [3:0] A;
input logic [3:0] B;
input logic [3:0] C;
input logic [3:0] D;
input logic [1:0]sel;
input logic en;

//    Output    //
output logic  [3:0] out;

//    Operation    //

  always @ (*) begin
        if (en) begin
            if (sel == 2'b00) begin 
                out <= A;
            end
            if (sel == 2'b01) begin 
                out <= B;
            end
            if (sel == 2'b10) begin 
                out <= C;
            end
            if (sel == 2'b11) begin 
                out <= D;
            end
        end
        else begin
            out = 3'bz;
        end
    end
endmodule

jerarquia/testbench.sv
/*
Name  : Nazim
Date  : 29th April, 2018
Design: 4x1 MUX test bench
*/


module mux ();
    reg [3:0]A;
    reg [3:0]B;
    reg [3:0]C;
    reg [3:0]D;
    reg [1:0]sel;
    reg en;
    wire [3:0] out;

MUX mux (
    .A (A),
    .B (B),
    .C (C),
    .D (D),
    .sel (sel),
    .en (en),
    .out (out)
);

initial forever #80 en  = ~en;
initial forever #20 sel  = sel+1;

initial begin
    A = $random;
    B = A - 1;
    C = A + 1;
    D = (2 * A ) + 1;
    sel = 0;
    en = 0;
end

initial begin 
    $dumpfile ("mux.vcd");
    $dumpvars;
end

initial begin 
    #320;
    $finish;
end
endmodule

jerarquia/mux.vcd
$date
	Thu Mar 20 05:35:03 2025
$end
$version
	Icarus Verilog
$end
$timescale
	1s
$end
$scope module mux $end
$var wire 4 ! out [3:0] $end
$var reg 4 " A [3:0] $end
$var reg 4 # B [3:0] $end
$var reg 4 $ C [3:0] $end
$var reg 4 % D [3:0] $end
$var reg 1 & en $end
$var reg 2 ' sel [1:0] $end
$scope module mux $end
$var wire 4 ( A [3:0] $end
$var wire 4 ) B [3:0] $end
$var wire 4 * C [3:0] $end
$var wire 4 + D [3:0] $end
$var wire 1 & en $end
$var wire 2 , sel [1:0] $end
$var reg 4 - out [3:0] $end
$upscope $end
$upscope $end
$enddefinitions $end
$comment Show the parameter values. $end
$dumpall
$end
#0
$dumpvars
b0zzz -
b0 ,
b1001 +
b101 *
b11 )
b100 (
b0 '
0&
b1001 %
b101 $
b11 #
b100 "
b0zzz !
$end
#20
b1 '
b1 ,
#40
b10 '
b10 ,
#60
b11 '
b11 ,
#80
b100 !
b100 -
b0 '
b0 ,
1&
#100
b11 !
b11 -
b1 '
b1 ,
#120
b101 !
b101 -
b10 '
b10 ,
#140
b1001 !
b1001 -
b11 '
b11 ,
#160
b0zzz !
b0zzz -
b0 '
b0 ,
0&
#180
b1 '
b1 ,
#200
b10 '
b10 ,
#220
b11 '
b11 ,
#240
b100 !
b100 -
b0 '
b0 ,
1&
#260
b11 !
b11 -
b1 '
b1 ,
#280
b101 !
b101 -
b10 '
b10 ,
#300
b1001 !
b1001 -
b11 '
b11 ,
#320
b0zzz !
b0zzz -
b0 '
b0 ,
0&
